peroxymanova-0.4.0.dist-info/METADATA
peroxymanova-0.4.0.dist-info/WHEEL
peroxymanova-0.4.0.dist-info/license_files/LICENSE.txt
peroxymanova/distance.py
peroxymanova/py.typed
peroxymanova/types.py
peroxymanova/_oxide.pyi
peroxymanova/_peroxymanova.py
peroxymanova/__init__.py
peroxymanova/_oxide.cp38-win_amd64.pyd
peroxymanova-0.4.0.dist-info/RECORD
