Metadata-Version: 2.3
Name: peroxymanova
Version: 0.4.0
Classifier: Programming Language :: Rust
Classifier: Programming Language :: Python :: Implementation :: CPython
Classifier: Programming Language :: Python :: Implementation :: PyPy
Requires-Dist: numpy >=1.15, <1.27
Requires-Dist: scipy >=1.1, <1.13
License-File: LICENSE.txt
Summary: 'ANOVA supercharged' supercharged
Requires-Python: >=3.8, <3.13
